awsparams/__init__.py
awsparams/cli.py
awsparams-1.5.5.dist-info/LICENSE
awsparams-1.5.5.dist-info/METADATA
awsparams-1.5.5.dist-info/WHEEL
awsparams-1.5.5.dist-info/entry_points.txt
awsparams-1.5.5.dist-info/RECORD
