Metadata-Version: 2.1
Name: awsparams
Version: 1.5.5
Summary: A simple CLI and Library for adding/removing/renaming/copying AWS Param Store Parameters
Home-page: https://github.com/byu-oit/awsparams
License: Apache-2.0
Author: Nate Peterson
Author-email: ndpete@gmail.com
Requires-Python: >=3.6,<4
Classifier: License :: OSI Approved :: Apache Software License
Classifier: Programming Language :: Python :: 3
Classifier: Programming Language :: Python :: 3.6
Classifier: Programming Language :: Python :: 3.7
Classifier: Programming Language :: Python :: 3.8
Classifier: Programming Language :: Python :: 3.9
Classifier: Programming Language :: Python :: 3.10
Classifier: Programming Language :: Python :: 3.11
Requires-Dist: boto3 (>=1.17.56,<2.0.0)
Requires-Dist: click (>=7.1.2,<8.0.0)
Project-URL: Repository, https://github.com/byu-oit/awsparams
